neontology/__init__.py
neontology/basenode.py
neontology/baserelationship.py
neontology/commonmodel.py
neontology/gql.py
neontology/graphconnection.py
neontology/result.py
neontology/schema_utils.py
neontology/utils.py
neontology/graphengines/__init__.py
neontology/graphengines/graphengine.py
neontology/graphengines/memgraphengine.py
neontology/graphengines/neo4jengine.py
neontology/graphengines/networkxengine.py
neontology/tools/__init__.py
neontology/tools/import_files.py
neontology/tools/import_records.py
neontology-2.2.2.dist-info/licenses/LICENSE
neontology-2.2.2.dist-info/METADATA
neontology-2.2.2.dist-info/WHEEL
neontology-2.2.2.dist-info/top_level.txt
neontology-2.2.2.dist-info/RECORD
