Metadata-Version: 2.4
Name: neontology
Version: 2.2.2
Summary: A Python package for modelling data in a Neo4j graph database with Pydantic and Pandas.
Author: Ontolocy
License-Expression: MIT
Project-URL: Homepage, https://github.com/ontolocy/neontology
Project-URL: Repository, https://github.com/ontolocy/neontology
Project-URL: Documentation, https://neontology.readthedocs.io/
Project-URL: Bug Tracker, https://github.com/ontolocy/neontology/issues
Classifier: Programming Language :: Python :: 3
Classifier: Programming Language :: Python :: 3 :: Only
Classifier: Programming Language :: Python :: 3.9
Classifier: Programming Language :: Python :: 3.10
Classifier: Programming Language :: Python :: 3.11
Classifier: Programming Language :: Python :: 3.12
Classifier: Programming Language :: Python :: 3.13
Classifier: Operating System :: OS Independent
Classifier: Intended Audience :: Developers
Classifier: Topic :: Software Development :: Libraries :: Python Modules
Classifier: Topic :: Database
Requires-Python: >=3.9
License-File: LICENSE
Requires-Dist: neo4j<6,>=5.0
Requires-Dist: pydantic<3,>=2.7
Requires-Dist: pandas<3,>=2.0
Requires-Dist: python-dotenv<2,>=1.0
Requires-Dist: Jinja2<4,>=3.0
Requires-Dist: typing-extensions<5,>=4.0
Requires-Dist: PyYAML<7,>=6.0
Provides-Extra: grand
Requires-Dist: grand-cypher>=0.13.0; extra == "grand"
Requires-Dist: networkx>=3.2.1; extra == "grand"
Provides-Extra: all
Requires-Dist: neontology[grand]; extra == "all"
Dynamic: license-file
